{
    "Meta Data": {
        "1. Information": "Intraday (60min) open, high, low, close prices and volume",
        "2. Symbol": "TSLA",
        "3. Last Refreshed": "2025-10-27 19:00:00",
        "4. Interval": "60min",
        "5. Output Size": "Full size",
        "6. Time Zone": "US/Eastern"
    },
    "Time Series (60min)": {
        "2025-10-27 19:00:00": {
            "1. open": "454.0945",
            "2. high": "455.8200",
            "3. low": "454.0000",
            "4. close": "455.6561",
            "5. volume": "315789"
        },
        "2025-10-27 18:00:00": {
            "1. open": "452.5500",
            "2. high": "454.3607",
            "3. low": "452.3000",
            "4. close": "454.0900",
            "5. volume": "216304"
        },
        "2025-10-27 17:00:00": {
            "1. open": "452.4800",
            "2. high": "456.6330",
            "3. low": "421.9151",
            "4. close": "452.5200",
            "5. volume": "133079"
        },
        "2025-10-27 16:00:00": {
            "1. open": "452.3400",
            "2. high": "453.3841",
            "3. low": "310.4951",
            "4. close": "452.5000",
            "5. volume": "9498075"
        },
        "2025-10-27 15:00:00": {
            "1. open": "455.2000",
            "2. high": "456.5100",
            "3. low": "447.2600",
            "4. close": "452.3500",
            "5. volume": "18780822"
        },
        "2025-10-27 14:00:00": {
            "1. open": "459.6400",
            "2. high": "460.1600",
            "3. low": "454.5200",
            "4. close": "455.2000",
            "5. volume": "10725019"
        },
        "2025-10-27 13:00:00": {
            "1. open": "457.7555",
            "2. high": "459.9900",
            "3. low": "447.9943",
            "4. close": "459.6500",
            "5. volume": "8411070"
        },
        "2025-10-27 12:00:00": {
            "1. open": "455.9295",
            "2. high": "459.1800",
            "3. low": "454.9200",
            "4. close": "457.7500",
            "5. volume": "12398581"
        },
        "2025-10-27 11:00:00": {
            "1. open": "447.0400",
            "2. high": "457.2100",
            "3. low": "445.9500",
            "4. close": "455.9017",
            "5. volume": "17848676"
        },
        "2025-10-27 10:00:00": {
            "1. open": "446.0450",
            "2. high": "450.5300",
            "3. low": "445.2500",
            "4. close": "447.1200",
            "5. volume": "16116624"
        },
        "2025-10-27 09:00:00": {
            "1. open": "438.7400",
            "2. high": "446.8500",
            "3. low": "438.6500",
            "4. close": "445.9900",
            "5. volume": "13803541"
        },
        "2025-10-27 08:00:00": {
            "1. open": "439.7800",
            "2. high": "441.3000",
            "3. low": "432.6360",
            "4. close": "438.7400",
            "5. volume": "896142"
        },
        "2025-10-27 07:00:00": {
            "1. open": "440.6400",
            "2. high": "441.1100",
            "3. low": "438.6500",
            "4. close": "439.8300",
            "5. volume": "332787"
        },
        "2025-10-27 06:00:00": {
            "1. open": "441.0800",
            "2. high": "441.3300",
            "3. low": "440.3900",
            "4. close": "440.6500",
            "5. volume": "124865"
        },
        "2025-10-27 05:00:00": {
            "1. open": "440.3100",
            "2. high": "441.3300",
            "3. low": "440.2200",
            "4. close": "441.1000",
            "5. volume": "141580"
        },
        "2025-10-27 04:00:00": {
            "1. open": "440.2300",
            "2. high": "440.9600",
            "3. low": "438.1400",
            "4. close": "440.2600",
            "5. volume": "313122"
        },
        "2025-10-24 19:00:00": {
            "1. open": "434.4500",
            "2. high": "434.5000",
            "3. low": "433.4300",
            "4. close": "433.7200",
            "5. volume": "172027"
        },
        "2025-10-24 18:00:00": {
            "1. open": "433.8600",
            "2. high": "434.6600",
            "3. low": "433.7200",
            "4. close": "434.4700",
            "5. volume": "182391"
        },
        "2025-10-24 17:00:00": {
            "1. open": "433.8750",
            "2. high": "433.9000",
            "3. low": "433.2400",
            "4. close": "433.8800",
            "5. volume": "149226"
        },
        "2025-10-24 16:00:00": {
            "1. open": "433.6400",
            "2. high": "434.2600",
            "3. low": "310.7800",
            "4. close": "433.8700",
            "5. volume": "8846505"
        },
        "2025-10-24 15:00:00": {
            "1. open": "432.5000",
            "2. high": "434.1400",
            "3. low": "430.1700",
            "4. close": "433.6500",
            "5. volume": "13670250"
        },
        "2025-10-24 14:00:00": {
            "1. open": "435.1995",
            "2. high": "436.7200",
            "3. low": "430.5000",
            "4. close": "432.4903",
            "5. volume": "10929386"
        },
        "2025-10-24 13:00:00": {
            "1. open": "436.7800",
            "2. high": "436.9900",
            "3. low": "433.6800",
            "4. close": "435.2550",
            "5. volume": "9909058"
        },
        "2025-10-24 12:00:00": {
            "1. open": "437.9700",
            "2. high": "439.0480",
            "3. low": "435.6000",
            "4. close": "436.7900",
            "5. volume": "9017672"
        },
        "2025-10-24 11:00:00": {
            "1. open": "438.4000",
            "2. high": "441.4900",
            "3. low": "437.0701",
            "4. close": "438.0000",
            "5. volume": "10231606"
        },
        "2025-10-24 10:00:00": {
            "1. open": "440.8700",
            "2. high": "447.3383",
            "3. low": "437.8400",
            "4. close": "438.4700",
            "5. volume": "17195518"
        },
        "2025-10-24 09:00:00": {
            "1. open": "447.0500",
            "2. high": "451.6800",
            "3. low": "420.2650",
            "4. close": "440.8000",
            "5. volume": "16273040"
        },
        "2025-10-24 08:00:00": {
            "1. open": "446.7600",
            "2. high": "449.5000",
            "3. low": "444.8000",
            "4. close": "447.1300",
            "5. volume": "1644976"
        },
        "2025-10-24 07:00:00": {
            "1. open": "446.8200",
            "2. high": "447.3000",
            "3. low": "446.0300",
            "4. close": "446.3400",
            "5. volume": "150760"
        },
        "2025-10-24 06:00:00": {
            "1. open": "447.3200",
            "2. high": "447.3900",
            "3. low": "446.6600",
            "4. close": "446.8300",
            "5. volume": "88486"
        },
        "2025-10-24 05:00:00": {
            "1. open": "447.0800",
            "2. high": "447.5000",
            "3. low": "446.7000",
            "4. close": "447.3400",
            "5. volume": "76542"
        },
        "2025-10-24 04:00:00": {
            "1. open": "447.0000",
            "2. high": "448.7700",
            "3. low": "445.5800",
            "4. close": "447.1000",
            "5. volume": "152344"
        },
        "2025-10-23 19:00:00": {
            "1. open": "447.2850",
            "2. high": "447.4500",
            "3. low": "446.1700",
            "4. close": "446.1900",
            "5. volume": "235627"
        },
        "2025-10-23 18:00:00": {
            "1. open": "446.7700",
            "2. high": "448.9800",
            "3. low": "446.6500",
            "4. close": "447.3500",
            "5. volume": "212547"
        },
        "2025-10-23 17:00:00": {
            "1. open": "447.2000",
            "2. high": "448.9800",
            "3. low": "446.6500",
            "4. close": "446.7700",
            "5. volume": "398728"
        },
        "2025-10-23 16:00:00": {
            "1. open": "449.0600",
            "2. high": "449.6000",
            "3. low": "438.9490",
            "4. close": "447.1993",
            "5. volume": "7537995"
        },
        "2025-10-23 15:00:00": {
            "1. open": "443.2600",
            "2. high": "449.3000",
            "3. low": "442.9500",
            "4. close": "448.9950",
            "5. volume": "15300543"
        },
        "2025-10-23 14:00:00": {
            "1. open": "446.8450",
            "2. high": "448.8400",
            "3. low": "441.5600",
            "4. close": "443.3200",
            "5. volume": "12700432"
        },
        "2025-10-23 13:00:00": {
            "1. open": "445.0000",
            "2. high": "449.3999",
            "3. low": "442.5800",
            "4. close": "446.8200",
            "5. volume": "17745888"
        },
        "2025-10-23 12:00:00": {
            "1. open": "433.9000",
            "2. high": "445.3452",
            "3. low": "432.7900",
            "4. close": "445.0328",
            "5. volume": "17326808"
        },
        "2025-10-23 11:00:00": {
            "1. open": "424.8650",
            "2. high": "433.9700",
            "3. low": "424.4400",
            "4. close": "433.9000",
            "5. volume": "15486101"
        },
        "2025-10-23 10:00:00": {
            "1. open": "422.4844",
            "2. high": "426.1900",
            "3. low": "420.5000",
            "4. close": "424.8650",
            "5. volume": "16395212"
        },
        "2025-10-23 09:00:00": {
            "1. open": "422.1314",
            "2. high": "425.5000",
            "3. low": "413.9000",
            "4. close": "422.4444",
            "5. volume": "23111888"
        },
        "2025-10-23 08:00:00": {
            "1. open": "422.0200",
            "2. high": "438.9700",
            "3. low": "420.8500",
            "4. close": "422.1800",
            "5. volume": "2208653"
        },
        "2025-10-23 07:00:00": {
            "1. open": "424.9800",
            "2. high": "426.5600",
            "3. low": "422.2100",
            "4. close": "422.2400",
            "5. volume": "336787"
        },
        "2025-10-23 06:00:00": {
            "1. open": "425.2300",
            "2. high": "425.4700",
            "3. low": "423.2400",
            "4. close": "425.1500",
            "5. volume": "208754"
        },
        "2025-10-23 05:00:00": {
            "1. open": "425.8500",
            "2. high": "426.4800",
            "3. low": "424.1900",
            "4. close": "425.2000",
            "5. volume": "145367"
        },
        "2025-10-23 04:00:00": {
            "1. open": "422.2200",
            "2. high": "427.5000",
            "3. low": "421.7600",
            "4. close": "425.8000",
            "5. volume": "409047"
        },
        "2025-10-22 19:00:00": {
            "1. open": "423.0900",
            "2. high": "424.3700",
            "3. low": "420.1000",
            "4. close": "422.3800",
            "5. volume": "968532"
        },
        "2025-10-22 18:00:00": {
            "1. open": "418.9900",
            "2. high": "438.9700",
            "3. low": "417.2200",
            "4. close": "423.1000",
            "5. volume": "2741905"
        },
        "2025-10-22 17:00:00": {
            "1. open": "431.6700",
            "2. high": "452.4129",
            "3. low": "418.7000",
            "4. close": "418.9200",
            "5. volume": "3396964"
        },
        "2025-10-22 16:00:00": {
            "1. open": "438.7050",
            "2. high": "461.5665",
            "3. low": "408.0781",
            "4. close": "431.8000",
            "5. volume": "10230907"
        },
        "2025-10-22 15:00:00": {
            "1. open": "436.2000",
            "2. high": "439.5900",
            "3. low": "435.1365",
            "4. close": "438.7200",
            "5. volume": "12369963"
        },
        "2025-10-22 14:00:00": {
            "1. open": "431.3700",
            "2. high": "436.4700",
            "3. low": "430.2000",
            "4. close": "436.2300",
            "5. volume": "7859058"
        },
        "2025-10-22 13:00:00": {
            "1. open": "434.2350",
            "2. high": "435.0900",
            "3. low": "429.5500",
            "4. close": "431.3850",
            "5. volume": "6690556"
        },
        "2025-10-22 12:00:00": {
            "1. open": "435.2350",
            "2. high": "436.3600",
            "3. low": "429.0000",
            "4. close": "434.2467",
            "5. volume": "8482378"
        },
        "2025-10-22 11:00:00": {
            "1. open": "437.5000",
            "2. high": "438.0900",
            "3. low": "431.8750",
            "4. close": "435.2415",
            "5. volume": "10149489"
        },
        "2025-10-22 10:00:00": {
            "1. open": "441.5200",
            "2. high": "441.9399",
            "3. low": "432.3500",
            "4. close": "437.4800",
            "5. volume": "14310209"
        },
        "2025-10-22 09:00:00": {
            "1. open": "442.7381",
            "2. high": "445.5390",
            "3. low": "439.6000",
            "4. close": "441.5600",
            "5. volume": "7947135"
        },
        "2025-10-22 08:00:00": {
            "1. open": "443.8000",
            "2. high": "445.0000",
            "3. low": "441.0400",
            "4. close": "442.7100",
            "5. volume": "600179"
        },
        "2025-10-22 07:00:00": {
            "1. open": "443.1500",
            "2. high": "443.5000",
            "3. low": "441.0200",
            "4. close": "441.4500",
            "5. volume": "218719"
        },
        "2025-10-22 06:00:00": {
            "1. open": "443.5400",
            "2. high": "444.1000",
            "3. low": "443.0000",
            "4. close": "443.0900",
            "5. volume": "79602"
        },
        "2025-10-22 05:00:00": {
            "1. open": "444.8100",
            "2. high": "444.9200",
            "3. low": "443.0000",
            "4. close": "443.5600",
            "5. volume": "96812"
        },
        "2025-10-22 04:00:00": {
            "1. open": "443.5000",
            "2. high": "445.0100",
            "3. low": "442.6400",
            "4. close": "444.8300",
            "5. volume": "203353"
        },
        "2025-10-21 19:00:00": {
            "1. open": "441.6100",
            "2. high": "441.9000",
            "3. low": "441.0600",
            "4. close": "441.7700",
            "5. volume": "152747"
        },
        "2025-10-21 18:00:00": {
            "1. open": "442.3200",
            "2. high": "442.4700",
            "3. low": "441.2800",
            "4. close": "441.6000",
            "5. volume": "173256"
        },
        "2025-10-21 17:00:00": {
            "1. open": "442.0900",
            "2. high": "450.0427",
            "3. low": "280.1150",
            "4. close": "442.3650",
            "5. volume": "160636"
        },
        "2025-10-21 16:00:00": {
            "1. open": "442.5000",
            "2. high": "463.1606",
            "3. low": "415.8999",
            "4. close": "442.0600",
            "5. volume": "4182310"
        },
        "2025-10-21 15:00:00": {
            "1. open": "445.7900",
            "2. high": "446.5500",
            "3. low": "442.5000",
            "4. close": "442.5000",
            "5. volume": "7012009"
        },
        "2025-10-21 14:00:00": {
            "1. open": "446.3268",
            "2. high": "446.4700",
            "3. low": "444.3200",
            "4. close": "445.7600",
            "5. volume": "4624989"
        },
        "2025-10-21 13:00:00": {
            "1. open": "446.1800",
            "2. high": "447.4796",
            "3. low": "444.7520",
            "4. close": "446.3525",
            "5. volume": "5050520"
        },
        "2025-10-21 12:00:00": {
            "1. open": "448.2500",
            "2. high": "449.3000",
            "3. low": "445.5301",
            "4. close": "446.1400",
            "5. volume": "6337317"
        },
        "2025-10-21 11:00:00": {
            "1. open": "445.5920",
            "2. high": "448.3800",
            "3. low": "444.6300",
            "4. close": "448.2990",
            "5. volume": "7792601"
        },
        "2025-10-21 10:00:00": {
            "1. open": "443.0800",
            "2. high": "446.6600",
            "3. low": "442.0500",
            "4. close": "445.5600",
            "5. volume": "9856635"
        },
        "2025-10-21 09:00:00": {
            "1. open": "446.0800",
            "2. high": "448.7500",
            "3. low": "442.1200",
            "4. close": "443.0400",
            "5. volume": "9333673"
        },
        "2025-10-21 08:00:00": {
            "1. open": "443.2900",
            "2. high": "447.4300",
            "3. low": "442.1800",
            "4. close": "446.1085",
            "5. volume": "588895"
        },
        "2025-10-21 07:00:00": {
            "1. open": "445.0000",
            "2. high": "446.4600",
            "3. low": "444.5600",
            "4. close": "445.9000",
            "5. volume": "193477"
        },
        "2025-10-21 06:00:00": {
            "1. open": "444.8500",
            "2. high": "445.4100",
            "3. low": "444.0800",
            "4. close": "444.8300",
            "5. volume": "82188"
        },
        "2025-10-21 05:00:00": {
            "1. open": "444.1200",
            "2. high": "445.2400",
            "3. low": "443.7300",
            "4. close": "444.8500",
            "5. volume": "123988"
        },
        "2025-10-21 04:00:00": {
            "1. open": "443.1800",
            "2. high": "445.7400",
            "3. low": "442.2600",
            "4. close": "444.1200",
            "5. volume": "217627"
        },
        "2025-10-20 19:00:00": {
            "1. open": "446.9145",
            "2. high": "447.4000",
            "3. low": "431.7382",
            "4. close": "446.9000",
            "5. volume": "144408"
        },
        "2025-10-20 18:00:00": {
            "1. open": "446.4700",
            "2. high": "455.3493",
            "3. low": "446.4500",
            "4. close": "446.9408",
            "5. volume": "243202"
        },
        "2025-10-20 17:00:00": {
            "1. open": "446.5600",
            "2. high": "468.2614",
            "3. low": "434.5977",
            "4. close": "446.5000",
            "5. volume": "102488"
        },
        "2025-10-20 16:00:00": {
            "1. open": "447.3300",
            "2. high": "450.4355",
            "3. low": "332.5000",
            "4. close": "446.6100",
            "5. volume": "6107821"
        },
        "2025-10-20 15:00:00": {
            "1. open": "446.3625",
            "2. high": "447.9800",
            "3. low": "444.9910",
            "4. close": "447.3500",
            "5. volume": "8103741"
        },
        "2025-10-20 14:00:00": {
            "1. open": "443.5916",
            "2. high": "446.6999",
            "3. low": "443.1100",
            "4. close": "446.3600",
            "5. volume": "5657621"
        },
        "2025-10-20 13:00:00": {
            "1. open": "443.7900",
            "2. high": "444.5398",
            "3. low": "441.9100",
            "4. close": "443.6000",
            "5. volume": "5075871"
        },
        "2025-10-20 12:00:00": {
            "1. open": "444.1850",
            "2. high": "447.2499",
            "3. low": "443.0500",
            "4. close": "443.8260",
            "5. volume": "6715558"
        },
        "2025-10-20 11:00:00": {
            "1. open": "443.5000",
            "2. high": "444.5600",
            "3. low": "440.6100",
            "4. close": "444.1600",
            "5. volume": "8012260"
        },
        "2025-10-20 10:00:00": {
            "1. open": "448.0000",
            "2. high": "449.8000",
            "3. low": "442.6800",
            "4. close": "443.5000",
            "5. volume": "12527717"
        },
        "2025-10-20 09:00:00": {
            "1. open": "444.5400",
            "2. high": "448.9300",
            "3. low": "441.1101",
            "4. close": "447.9550",
            "5. volume": "11930453"
        },
        "2025-10-20 08:00:00": {
            "1. open": "445.5547",
            "2. high": "446.0000",
            "3. low": "439.3100",
            "4. close": "444.5800",
            "5. volume": "715992"
        },
        "2025-10-20 07:00:00": {
            "1. open": "443.8000",
            "2. high": "444.5000",
            "3. low": "443.1800",
            "4. close": "443.7000",
            "5. volume": "189007"
        },
        "2025-10-20 06:00:00": {
            "1. open": "444.3200",
            "2. high": "445.3700",
            "3. low": "443.7900",
            "4. close": "443.9000",
            "5. volume": "153511"
        },
        "2025-10-20 05:00:00": {
            "1. open": "443.8700",
            "2. high": "444.7000",
            "3. low": "443.2000",
            "4. close": "444.3000",
            "5. volume": "99737"
        },
        "2025-10-20 04:00:00": {
            "1. open": "443.2000",
            "2. high": "446.0000",
            "3. low": "441.7500",
            "4. close": "443.9400",
            "5. volume": "392335"
        },
        "2025-10-17 19:00:00": {
            "1. open": "439.1200",
            "2. high": "439.8050",
            "3. low": "439.1100",
            "4. close": "439.7700",
            "5. volume": "108580"
        },
        "2025-10-17 18:00:00": {
            "1. open": "439.0650",
            "2. high": "439.3500",
            "3. low": "420.8024",
            "4. close": "439.1200",
            "5. volume": "131454"
        },
        "2025-10-17 17:00:00": {
            "1. open": "439.1200",
            "2. high": "466.6321",
            "3. low": "420.6809",
            "4. close": "439.0400",
            "5. volume": "326307"
        },
        "2025-10-17 16:00:00": {
            "1. open": "439.2700",
            "2. high": "457.4448",
            "3. low": "420.6809",
            "4. close": "439.1550",
            "5. volume": "6570560"
        },
        "2025-10-17 15:00:00": {
            "1. open": "437.6950",
            "2. high": "441.4558",
            "3. low": "437.0500",
            "4. close": "439.2700",
            "5. volume": "11907734"
        },
        "2025-10-17 14:00:00": {
            "1. open": "438.8300",
            "2. high": "440.4000",
            "3. low": "426.9700",
            "4. close": "437.6901",
            "5. volume": "8747176"
        },
        "2025-10-17 13:00:00": {
            "1. open": "436.3000",
            "2. high": "439.8500",
            "3. low": "434.8958",
            "4. close": "438.8700",
            "5. volume": "7548563"
        },
        "2025-10-17 12:00:00": {
            "1. open": "435.2901",
            "2. high": "439.3700",
            "3. low": "435.1620",
            "4. close": "436.3000",
            "5. volume": "9700356"
        },
        "2025-10-17 11:00:00": {
            "1. open": "433.9700",
            "2. high": "436.5500",
            "3. low": "430.8000",
            "4. close": "435.3761",
            "5. volume": "11399170"
        },
        "2025-10-17 10:00:00": {
            "1. open": "432.8600",
            "2. high": "440.7500",
            "3. low": "431.1500",
            "4. close": "434.0170",
            "5. volume": "20398606"
        },
        "2025-10-17 09:00:00": {
            "1. open": "425.0400",
            "2. high": "434.1500",
            "3. low": "423.6000",
            "4. close": "432.9200",
            "5. volume": "12056013"
        },
        "2025-10-17 08:00:00": {
            "1. open": "426.0600",
            "2. high": "428.7500",
            "3. low": "415.1300",
            "4. close": "425.0100",
            "5. volume": "1533123"
        },
        "2025-10-17 07:00:00": {
            "1. open": "421.1900",
            "2. high": "426.0600",
            "3. low": "421.0000",
            "4. close": "426.0600",
            "5. volume": "528597"
        },
        "2025-10-17 06:00:00": {
            "1. open": "418.8100",
            "2. high": "421.5000",
            "3. low": "417.3200",
            "4. close": "421.2000",
            "5. volume": "230361"
        },
        "2025-10-17 05:00:00": {
            "1. open": "417.8000",
            "2. high": "419.9900",
            "3. low": "417.7500",
            "4. close": "418.7000",
            "5. volume": "274907"
        },
        "2025-10-17 04:00:00": {
            "1. open": "420.1800",
            "2. high": "420.7400",
            "3. low": "415.1300",
            "4. close": "417.8100",
            "5. volume": "655941"
        },
        "2025-10-16 19:00:00": {
            "1. open": "426.7900",
            "2. high": "426.7900",
            "3. low": "424.7100",
            "4. close": "424.9000",
            "5. volume": "253081"
        },
        "2025-10-16 18:00:00": {
            "1. open": "427.3400",
            "2. high": "428.7500",
            "3. low": "426.4000",
            "4. close": "426.5300",
            "5. volume": "146916"
        },
        "2025-10-16 17:00:00": {
            "1. open": "427.8900",
            "2. high": "428.2000",
            "3. low": "416.6151",
            "4. close": "427.3050",
            "5. volume": "204199"
        },
        "2025-10-16 16:00:00": {
            "1. open": "428.5900",
            "2. high": "433.9217",
            "3. low": "416.6151",
            "4. close": "427.8900",
            "5. volume": "5544806"
        },
        "2025-10-16 15:00:00": {
            "1. open": "426.8600",
            "2. high": "430.4399",
            "3. low": "423.7500",
            "4. close": "428.5850",
            "5. volume": "10582798"
        },
        "2025-10-16 14:00:00": {
            "1. open": "428.1700",
            "2. high": "428.7958",
            "3. low": "421.3101",
            "4. close": "426.8940",
            "5. volume": "11347747"
        },
        "2025-10-16 13:00:00": {
            "1. open": "431.3800",
            "2. high": "431.9900",
            "3. low": "427.4600",
            "4. close": "428.2150",
            "5. volume": "7278817"
        },
        "2025-10-16 12:00:00": {
            "1. open": "432.8900",
            "2. high": "433.1399",
            "3. low": "425.8100",
            "4. close": "431.3926",
            "5. volume": "12705039"
        },
        "2025-10-16 11:00:00": {
            "1. open": "436.4800",
            "2. high": "438.4100",
            "3. low": "432.2835",
            "4. close": "432.9450",
            "5. volume": "9095061"
        },
        "2025-10-16 10:00:00": {
            "1. open": "435.1800",
            "2. high": "439.3500",
            "3. low": "434.4500",
            "4. close": "436.4177",
            "5. volume": "11865709"
        },
        "2025-10-16 09:00:00": {
            "1. open": "436.0800",
            "2. high": "437.2100",
            "3. low": "431.7500",
            "4. close": "435.0500",
            "5. volume": "9409957"
        },
        "2025-10-16 08:00:00": {
            "1. open": "435.5000",
            "2. high": "436.8400",
            "3. low": "432.2000",
            "4. close": "436.0900",
            "5. volume": "656903"
        },
        "2025-10-16 07:00:00": {
            "1. open": "435.0500",
            "2. high": "436.8400",
            "3. low": "434.9600",
            "4. close": "436.4500",
            "5. volume": "163372"
        },
        "2025-10-16 06:00:00": {
            "1. open": "434.7000",
            "2. high": "435.8900",
            "3. low": "434.5300",
            "4. close": "435.0800",
            "5. volume": "81889"
        },
        "2025-10-16 05:00:00": {
            "1. open": "435.4500",
            "2. high": "435.5900",
            "3. low": "434.1800",
            "4. close": "434.6700",
            "5. volume": "97863"
        },
        "2025-10-16 04:00:00": {
            "1. open": "434.0000",
            "2. high": "436.3200",
            "3. low": "433.7000",
            "4. close": "435.4900",
            "5. volume": "156892"
        },
        "2025-10-15 19:00:00": {
            "1. open": "435.4400",
            "2. high": "435.6000",
            "3. low": "434.2801",
            "4. close": "434.4500",
            "5. volume": "114890"
        },
        "2025-10-15 18:00:00": {
            "1. open": "435.7800",
            "2. high": "436.1500",
            "3. low": "435.1000",
            "4. close": "435.4900",
            "5. volume": "94620"
        },
        "2025-10-15 17:00:00": {
            "1. open": "435.7850",
            "2. high": "436.0800",
            "3. low": "406.5476",
            "4. close": "435.7500",
            "5. volume": "126637"
        },
        "2025-10-15 16:00:00": {
            "1. open": "435.1700",
            "2. high": "449.5258",
            "3. low": "347.7900",
            "4. close": "435.7700",
            "5. volume": "4791414"
        },
        "2025-10-15 15:00:00": {
            "1. open": "434.4100",
            "2. high": "435.4300",
            "3. low": "431.8400",
            "4. close": "435.1900",
            "5. volume": "8470946"
        },
        "2025-10-15 14:00:00": {
            "1. open": "432.7600",
            "2. high": "434.5000",
            "3. low": "430.5200",
            "4. close": "434.4450",
            "5. volume": "5904451"
        },
        "2025-10-15 13:00:00": {
            "1. open": "433.2200",
            "2. high": "433.2582",
            "3. low": "426.3301",
            "4. close": "432.7500",
            "5. volume": "9866356"
        },
        "2025-10-15 12:00:00": {
            "1. open": "433.4560",
            "2. high": "435.5862",
            "3. low": "432.5100",
            "4. close": "433.1780",
            "5. volume": "6044976"
        },
        "2025-10-15 11:00:00": {
            "1. open": "436.8850",
            "2. high": "438.1890",
            "3. low": "431.2400",
            "4. close": "433.4000",
            "5. volume": "12225750"
        },
        "2025-10-15 10:00:00": {
            "1. open": "435.6150",
            "2. high": "440.5100",
            "3. low": "434.0501",
            "4. close": "436.9000",
            "5. volume": "13799248"
        },
        "2025-10-15 09:00:00": {
            "1. open": "434.9700",
            "2. high": "438.8060",
            "3. low": "429.7000",
            "4. close": "435.6150",
            "5. volume": "10717984"
        },
        "2025-10-15 08:00:00": {
            "1. open": "435.1100",
            "2. high": "435.8200",
            "3. low": "429.2400",
            "4. close": "434.9700",
            "5. volume": "743988"
        },
        "2025-10-15 07:00:00": {
            "1. open": "434.2400",
            "2. high": "434.7100",
            "3. low": "433.5000",
            "4. close": "433.5200",
            "5. volume": "150127"
        },
        "2025-10-15 06:00:00": {
            "1. open": "434.6700",
            "2. high": "435.0400",
            "3. low": "434.2200",
            "4. close": "434.2600",
            "5. volume": "85238"
        },
        "2025-10-15 05:00:00": {
            "1. open": "434.8800",
            "2. high": "435.3500",
            "3. low": "433.9300",
            "4. close": "434.6200",
            "5. volume": "100253"
        },
        "2025-10-15 04:00:00": {
            "1. open": "433.6900",
            "2. high": "435.8000",
            "3. low": "432.7500",
            "4. close": "434.8800",
            "5. volume": "269472"
        },
        "2025-10-14 19:00:00": {
            "1. open": "428.6000",
            "2. high": "429.8000",
            "3. low": "428.5000",
            "4. close": "428.9700",
            "5. volume": "117533"
        },
        "2025-10-14 18:00:00": {
            "1. open": "429.4000",
            "2. high": "430.2700",
            "3. low": "428.5100",
            "4. close": "428.6100",
            "5. volume": "127700"
        },
        "2025-10-14 17:00:00": {
            "1. open": "429.3400",
            "2. high": "459.4827",
            "3. low": "403.0373",
            "4. close": "429.4000",
            "5. volume": "125495"
        },
        "2025-10-14 16:00:00": {
            "1. open": "429.1600",
            "2. high": "451.8844",
            "3. low": "415.9485",
            "4. close": "429.2800",
            "5. volume": "6977156"
        },
        "2025-10-14 15:00:00": {
            "1. open": "430.6820",
            "2. high": "433.1990",
            "3. low": "426.8800",
            "4. close": "429.2500",
            "5. volume": "9704463"
        },
        "2025-10-14 14:00:00": {
            "1. open": "431.9300",
            "2. high": "434.1500",
            "3. low": "430.5001",
            "4. close": "430.7175",
            "5. volume": "5352929"
        },
        "2025-10-14 13:00:00": {
            "1. open": "430.1000",
            "2. high": "433.4000",
            "3. low": "428.8800",
            "4. close": "431.9512",
            "5. volume": "6438947"
        },
        "2025-10-14 12:00:00": {
            "1. open": "427.4200",
            "2. high": "434.2000",
            "3. low": "418.8600",
            "4. close": "430.1200",
            "5. volume": "9626172"
        },
        "2025-10-14 11:00:00": {
            "1. open": "423.6900",
            "2. high": "429.3399",
            "3. low": "422.4000",
            "4. close": "427.3700",
            "5. volume": "9228692"
        },
        "2025-10-14 10:00:00": {
            "1. open": "419.8800",
            "2. high": "425.3499",
            "3. low": "418.8200",
            "4. close": "423.6650",
            "5. volume": "11696529"
        },
        "2025-10-14 09:00:00": {
            "1. open": "425.9500",
            "2. high": "426.8800",
            "3. low": "417.8600",
            "4. close": "420.0200",
            "5. volume": "12765681"
        },
        "2025-10-14 08:00:00": {
            "1. open": "426.8000",
            "2. high": "435.9000",
            "3. low": "413.4900",
            "4. close": "425.8800",
            "5. volume": "1740140"
        },
        "2025-10-14 07:00:00": {
            "1. open": "424.1200",
            "2. high": "426.9000",
            "3. low": "423.9700",
            "4. close": "426.8300",
            "5. volume": "374585"
        },
        "2025-10-14 06:00:00": {
            "1. open": "424.9500",
            "2. high": "424.9800",
            "3. low": "422.0000",
            "4. close": "424.0700",
            "5. volume": "297746"
        },
        "2025-10-14 05:00:00": {
            "1. open": "425.5200",
            "2. high": "426.8000",
            "3. low": "423.6600",
            "4. close": "424.9800",
            "5. volume": "231673"
        },
        "2025-10-14 04:00:00": {
            "1. open": "426.3400",
            "2. high": "428.7400",
            "3. low": "421.8000",
            "4. close": "425.5400",
            "5. volume": "473913"
        },
        "2025-10-13 19:00:00": {
            "1. open": "435.2700",
            "2. high": "435.5000",
            "3. low": "434.7700",
            "4. close": "435.5000",
            "5. volume": "132739"
        },
        "2025-10-13 18:00:00": {
            "1. open": "435.1000",
            "2. high": "435.4000",
            "3. low": "434.4400",
            "4. close": "435.2500",
            "5. volume": "107326"
        },
        "2025-10-13 17:00:00": {
            "1. open": "435.0500",
            "2. high": "450.0599",
            "3. low": "414.2383",
            "4. close": "435.0600",
            "5. volume": "339130"
        },
        "2025-10-13 16:00:00": {
            "1. open": "435.8800",
            "2. high": "436.7899",
            "3. low": "429.7775",
            "4. close": "435.0300",
            "5. volume": "10577414"
        },
        "2025-10-13 15:00:00": {
            "1. open": "432.9550",
            "2. high": "436.5000",
            "3. low": "431.6400",
            "4. close": "435.9000",
            "5. volume": "11598123"
        },
        "2025-10-13 14:00:00": {
            "1. open": "431.4125",
            "2. high": "436.8900",
            "3. low": "426.7250",
            "4. close": "432.9600",
            "5. volume": "11852044"
        },
        "2025-10-13 13:00:00": {
            "1. open": "428.2400",
            "2. high": "431.5400",
            "3. low": "427.0508",
            "4. close": "431.4600",
            "5. volume": "7918348"
        },
        "2025-10-13 12:00:00": {
            "1. open": "425.9000",
            "2. high": "428.7000",
            "3. low": "425.6000",
            "4. close": "428.2000",
            "5. volume": "6445957"
        },
        "2025-10-13 11:00:00": {
            "1. open": "422.1400",
            "2. high": "426.6800",
            "3. low": "421.3000",
            "4. close": "425.8600",
            "5. volume": "7860247"
        },
        "2025-10-13 10:00:00": {
            "1. open": "424.0300",
            "2. high": "428.9900",
            "3. low": "420.1000",
            "4. close": "422.1000",
            "5. volume": "13307311"
        },
        "2025-10-13 09:00:00": {
            "1. open": "421.9200",
            "2. high": "426.5100",
            "3. low": "419.7000",
            "4. close": "424.1550",
            "5. volume": "10706709"
        },
        "2025-10-13 08:00:00": {
            "1. open": "422.5000",
            "2. high": "433.3150",
            "3. low": "416.0000",
            "4. close": "421.9200",
            "5. volume": "1638200"
        },
        "2025-10-13 07:00:00": {
            "1. open": "424.4500",
            "2. high": "424.7300",
            "3. low": "420.5000",
            "4. close": "422.5000",
            "5. volume": "652975"
        },
        "2025-10-13 06:00:00": {
            "1. open": "425.1200",
            "2. high": "425.7000",
            "3. low": "424.1200",
            "4. close": "424.4900",
            "5. volume": "255590"
        },
        "2025-10-13 05:00:00": {
            "1. open": "424.6800",
            "2. high": "425.2600",
            "3. low": "423.4900",
            "4. close": "425.0600",
            "5. volume": "261624"
        },
        "2025-10-13 04:00:00": {
            "1. open": "423.1000",
            "2. high": "424.9900",
            "3. low": "419.0200",
            "4. close": "424.6100",
            "5. volume": "537180"
        },
        "2025-10-10 19:00:00": {
            "1. open": "409.1000",
            "2. high": "411.7000",
            "3. low": "407.2000",
            "4. close": "408.0900",
            "5. volume": "661241"
        },
        "2025-10-10 18:00:00": {
            "1. open": "406.4000",
            "2. high": "439.4168",
            "3. low": "391.2652",
            "4. close": "409.1500",
            "5. volume": "1118861"
        },
        "2025-10-10 17:00:00": {
            "1. open": "407.8600",
            "2. high": "432.5444",
            "3. low": "380.4042",
            "4. close": "406.3900",
            "5. volume": "2239189"
        },
        "2025-10-10 16:00:00": {
            "1. open": "413.2500",
            "2. high": "435.6952",
            "3. low": "406.2200",
            "4. close": "407.7100",
            "5. volume": "12938925"
        },
        "2025-10-10 15:00:00": {
            "1. open": "416.6400",
            "2. high": "418.5990",
            "3. low": "411.4500",
            "4. close": "413.2700",
            "5. volume": "17228792"
        },
        "2025-10-10 14:00:00": {
            "1. open": "418.5000",
            "2. high": "419.9200",
            "3. low": "415.8000",
            "4. close": "416.6750",
            "5. volume": "7433920"
        },
        "2025-10-10 13:00:00": {
            "1. open": "418.4100",
            "2. high": "420.3499",
            "3. low": "415.4400",
            "4. close": "418.4700",
            "5. volume": "11138431"
        },
        "2025-10-10 12:00:00": {
            "1. open": "424.7100",
            "2. high": "424.8600",
            "3. low": "417.3501",
            "4. close": "418.5050",
            "5. volume": "11572019"
        },
        "2025-10-10 11:00:00": {
            "1. open": "434.9600",
            "2. high": "435.1100",
            "3. low": "416.0100",
            "4. close": "424.7800",
            "5. volume": "26806636"
        },
        "2025-10-10 10:00:00": {
            "1. open": "437.8000",
            "2. high": "440.2500",
            "3. low": "433.3100",
            "4. close": "434.9450",
            "5. volume": "12642961"
        },
        "2025-10-10 09:00:00": {
            "1. open": "436.0500",
            "2. high": "443.1300",
            "3. low": "435.5400",
            "4. close": "437.8000",
            "5. volume": "12129507"
        },
        "2025-10-10 08:00:00": {
            "1. open": "437.5600",
            "2. high": "438.3000",
            "3. low": "432.6000",
            "4. close": "436.0000",
            "5. volume": "666156"
        },
        "2025-10-10 07:00:00": {
            "1. open": "436.0800",
            "2. high": "437.6600",
            "3. low": "435.3600",
            "4. close": "437.5800",
            "5. volume": "176986"
        },
        "2025-10-10 06:00:00": {
            "1. open": "433.5000",
            "2. high": "436.3000",
            "3. low": "433.4300",
            "4. close": "436.0900",
            "5. volume": "124927"
        },
        "2025-10-10 05:00:00": {
            "1. open": "436.7700",
            "2. high": "436.9000",
            "3. low": "432.6100",
            "4. close": "433.5000",
            "5. volume": "211025"
        },
        "2025-10-10 04:00:00": {
            "1. open": "435.6000",
            "2. high": "438.3200",
            "3. low": "434.6000",
            "4. close": "436.8000",
            "5. volume": "231531"
        },
        "2025-10-09 19:00:00": {
            "1. open": "435.3000",
            "2. high": "435.5000",
            "3. low": "434.7500",
            "4. close": "434.9200",
            "5. volume": "128622"
        },
        "2025-10-09 18:00:00": {
            "1. open": "434.9450",
            "2. high": "435.8000",
            "3. low": "434.9000",
            "4. close": "435.3000",
            "5. volume": "116284"
        },
        "2025-10-09 17:00:00": {
            "1. open": "435.1500",
            "2. high": "436.0858",
            "3. low": "407.0123",
            "4. close": "434.9900",
            "5. volume": "99981"
        },
        "2025-10-09 16:00:00": {
            "1. open": "435.4600",
            "2. high": "445.0000",
            "3. low": "296.1480",
            "4. close": "435.1500",
            "5. volume": "3933174"
        },
        "2025-10-09 15:00:00": {
            "1. open": "433.8700",
            "2. high": "436.3500",
            "3. low": "433.5186",
            "4. close": "435.5300",
            "5. volume": "9357193"
        },
        "2025-10-09 14:00:00": {
            "1. open": "430.8500",
            "2. high": "434.2000",
            "3. low": "429.8099",
            "4. close": "433.8300",
            "5. volume": "6219908"
        },
        "2025-10-09 13:00:00": {
            "1. open": "431.8600",
            "2. high": "432.3612",
            "3. low": "427.4590",
            "4. close": "430.8000",
            "5. volume": "8061301"
        },
        "2025-10-09 12:00:00": {
            "1. open": "429.7000",
            "2. high": "434.0000",
            "3. low": "429.3600",
            "4. close": "431.8159",
            "5. volume": "7641832"
        },
        "2025-10-09 11:00:00": {
            "1. open": "430.1000",
            "2. high": "431.3700",
            "3. low": "428.7000",
            "4. close": "429.6472",
            "5. volume": "7435498"
        },
        "2025-10-09 10:00:00": {
            "1. open": "430.7650",
            "2. high": "433.3904",
            "3. low": "426.1800",
            "4. close": "430.0100",
            "5. volume": "14137054"
        },
        "2025-10-09 09:00:00": {
            "1. open": "432.8700",
            "2. high": "434.3400",
            "3. low": "427.5100",
            "4. close": "430.6901",
            "5. volume": "11341216"
        },
        "2025-10-09 08:00:00": {
            "1. open": "435.0000",
            "2. high": "438.6900",
            "3. low": "429.5400",
            "4. close": "432.8500",
            "5. volume": "1335847"
        },
        "2025-10-09 07:00:00": {
            "1. open": "434.7000",
            "2. high": "435.5000",
            "3. low": "431.1100",
            "4. close": "432.4000",
            "5. volume": "446945"
        },
        "2025-10-09 06:00:00": {
            "1. open": "434.4200",
            "2. high": "435.2000",
            "3. low": "433.7900",
            "4. close": "434.7900",
            "5. volume": "99729"
        },
        "2025-10-09 05:00:00": {
            "1. open": "434.5000",
            "2. high": "435.4000",
            "3. low": "433.2800",
            "4. close": "434.3700",
            "5. volume": "165554"
        },
        "2025-10-09 04:00:00": {
            "1. open": "436.1400",
            "2. high": "462.7800",
            "3. low": "432.8000",
            "4. close": "434.5400",
            "5. volume": "239699"
        },
        "2025-10-08 19:00:00": {
            "1. open": "437.9200",
            "2. high": "438.5500",
            "3. low": "437.8104",
            "4. close": "437.8200",
            "5. volume": "144888"
        },
        "2025-10-08 18:00:00": {
            "1. open": "436.9400",
            "2. high": "439.0600",
            "3. low": "436.8100",
            "4. close": "437.9200",
            "5. volume": "112234"
        },
        "2025-10-08 17:00:00": {
            "1. open": "438.0500",
            "2. high": "438.6900",
            "3. low": "436.5000",
            "4. close": "436.8500",
            "5. volume": "758595"
        },
        "2025-10-08 16:00:00": {
            "1. open": "438.6000",
            "2. high": "439.2500",
            "3. low": "408.0781",
            "4. close": "438.0500",
            "5. volume": "5817011"
        },
        "2025-10-08 15:00:00": {
            "1. open": "437.2400",
            "2. high": "440.0900",
            "3. low": "435.8100",
            "4. close": "438.6000",
            "5. volume": "8475628"
        },
        "2025-10-08 14:00:00": {
            "1. open": "436.2550",
            "2. high": "441.3300",
            "3. low": "435.9549",
            "4. close": "437.1620",
            "5. volume": "8904769"
        },
        "2025-10-08 13:00:00": {
            "1. open": "435.6300",
            "2. high": "437.3000",
            "3. low": "434.1500",
            "4. close": "436.2532",
            "5. volume": "6440244"
        },
        "2025-10-08 12:00:00": {
            "1. open": "434.8450",
            "2. high": "435.9800",
            "3. low": "432.9600",
            "4. close": "435.6100",
            "5. volume": "5659279"
        },
        "2025-10-08 11:00:00": {
            "1. open": "432.2300",
            "2. high": "436.1900",
            "3. low": "431.6000",
            "4. close": "434.8500",
            "5. volume": "8122415"
        },
        "2025-10-08 10:00:00": {
            "1. open": "432.2550",
            "2. high": "435.5900",
            "3. low": "430.3201",
            "4. close": "432.2650",
            "5. volume": "12407853"
        },
        "2025-10-08 09:00:00": {
            "1. open": "435.6000",
            "2. high": "437.9400",
            "3. low": "425.2300",
            "4. close": "432.2745",
            "5. volume": "14594291"
        },
        "2025-10-08 08:00:00": {
            "1. open": "436.2900",
            "2. high": "438.9900",
            "3. low": "433.0900",
            "4. close": "435.5200",
            "5. volume": "1217017"
        },
        "2025-10-08 07:00:00": {
            "1. open": "436.0700",
            "2. high": "436.4400",
            "3. low": "434.0800",
            "4. close": "434.4100",
            "5. volume": "235786"
        },
        "2025-10-08 06:00:00": {
            "1. open": "437.0400",
            "2. high": "437.5700",
            "3. low": "434.8300",
            "4. close": "436.1000",
            "5. volume": "174060"
        },
        "2025-10-08 05:00:00": {
            "1. open": "437.9800",
            "2. high": "438.2600",
            "3. low": "436.5200",
            "4. close": "437.0900",
            "5. volume": "134957"
        },
        "2025-10-08 04:00:00": {
            "1. open": "437.2800",
            "2. high": "438.9600",
            "3. low": "436.6600",
            "4. close": "438.0700",
            "5. volume": "245793"
        },
        "2025-10-07 19:00:00": {
            "1. open": "436.8500",
            "2. high": "437.2000",
            "3. low": "436.0500",
            "4. close": "437.0000",
            "5. volume": "287298"
        },
        "2025-10-07 18:00:00": {
            "1. open": "434.8712",
            "2. high": "437.0000",
            "3. low": "434.7000",
            "4. close": "436.6800",
            "5. volume": "253805"
        },
        "2025-10-07 17:00:00": {
            "1. open": "435.3300",
            "2. high": "457.7728",
            "3. low": "415.8999",
            "4. close": "434.9000",
            "5. volume": "432782"
        },
        "2025-10-07 16:00:00": {
            "1. open": "432.9300",
            "2. high": "463.1606",
            "3. low": "334.0900",
            "4. close": "435.2850",
            "5. volume": "9809469"
        },
        "2025-10-07 15:00:00": {
            "1. open": "440.8750",
            "2. high": "442.2200",
            "3. low": "432.4501",
            "4. close": "432.8700",
            "5. volume": "19858585"
        },
        "2025-10-07 14:00:00": {
            "1. open": "447.3600",
            "2. high": "450.0100",
            "3. low": "437.7401",
            "4. close": "440.8300",
            "5. volume": "15353087"
        },
        "2025-10-07 13:00:00": {
            "1. open": "446.1450",
            "2. high": "450.1999",
            "3. low": "445.7301",
            "4. close": "447.2800",
            "5. volume": "7975443"
        },
        "2025-10-07 12:00:00": {
            "1. open": "441.1400",
            "2. high": "446.7400",
            "3. low": "440.1400",
            "4. close": "446.1205",
            "5. volume": "9182332"
        },
        "2025-10-07 11:00:00": {
            "1. open": "447.5100",
            "2. high": "448.1500",
            "3. low": "436.3210",
            "4. close": "441.1399",
            "5. volume": "15114409"
        },
        "2025-10-07 10:00:00": {
            "1. open": "450.7100",
            "2. high": "452.6800",
            "3. low": "445.7000",
            "4. close": "447.4650",
            "5. volume": "12142749"
        },
        "2025-10-07 09:00:00": {
            "1. open": "448.5400",
            "2. high": "453.2500",
            "3. low": "442.2900",
            "4. close": "450.6350",
            "5. volume": "12311080"
        },
        "2025-10-07 08:00:00": {
            "1. open": "451.0200",
            "2. high": "456.0500",
            "3. low": "416.8500",
            "4. close": "448.5000",
            "5. volume": "1809254"
        },
        "2025-10-07 07:00:00": {
            "1. open": "450.6200",
            "2. high": "451.2200",
            "3. low": "448.6800",
            "4. close": "451.0000",
            "5. volume": "254760"
        },
        "2025-10-07 06:00:00": {
            "1. open": "452.3800",
            "2. high": "452.4400",
            "3. low": "448.0100",
            "4. close": "450.5000",
            "5. volume": "346910"
        },
        "2025-10-07 05:00:00": {
            "1. open": "451.4300",
            "2. high": "453.5600",
            "3. low": "450.7700",
            "4. close": "452.3600",
            "5. volume": "181385"
        },
        "2025-10-07 04:00:00": {
            "1. open": "453.7000",
            "2. high": "454.3300",
            "3. low": "447.6000",
            "4. close": "451.5000",
            "5. volume": "436947"
        },
        "2025-10-06 19:00:00": {
            "1. open": "452.7000",
            "2. high": "454.0000",
            "3. low": "452.1600",
            "4. close": "453.9600",
            "5. volume": "204843"
        },
        "2025-10-06 18:00:00": {
            "1. open": "453.6200",
            "2. high": "454.0000",
            "3. low": "432.7671",
            "4. close": "452.6000",
            "5. volume": "287639"
        },
        "2025-10-06 17:00:00": {
            "1. open": "454.1900",
            "2. high": "468.2614",
            "3. low": "429.6400",
            "4. close": "453.6800",
            "5. volume": "968772"
        },
        "2025-10-06 16:00:00": {
            "1. open": "453.3700",
            "2. high": "454.9800",
            "3. low": "436.9700",
            "4. close": "454.1400",
            "5. volume": "9402970"
        },
        "2025-10-06 15:00:00": {
            "1. open": "450.6400",
            "2. high": "453.5500",
            "3. low": "449.8200",
            "4. close": "453.3600",
            "5. volume": "13530788"
        },
        "2025-10-06 14:00:00": {
            "1. open": "448.2900",
            "2. high": "450.7400",
            "3. low": "447.9100",
            "4. close": "450.6450",
            "5. volume": "6410045"
        },
        "2025-10-06 13:00:00": {
            "1. open": "448.5450",
            "2. high": "449.9900",
            "3. low": "447.2750",
            "4. close": "448.2501",
            "5. volume": "6379551"
        },
        "2025-10-06 12:00:00": {
            "1. open": "446.8900",
            "2. high": "449.1900",
            "3. low": "444.7011",
            "4. close": "448.5200",
            "5. volume": "8135685"
        },
        "2025-10-06 11:00:00": {
            "1. open": "444.7449",
            "2. high": "447.9100",
            "3. low": "444.1800",
            "4. close": "446.8825",
            "5. volume": "9556660"
        },
        "2025-10-06 10:00:00": {
            "1. open": "439.9550",
            "2. high": "447.4300",
            "3. low": "439.3000",
            "4. close": "444.6851",
            "5. volume": "15266099"
        },
        "2025-10-06 09:00:00": {
            "1. open": "441.1000",
            "2. high": "447.1000",
            "3. low": "436.6900",
            "4. close": "439.9550",
            "5. volume": "15926374"
        },
        "2025-10-06 08:00:00": {
            "1. open": "439.2500",
            "2. high": "441.1800",
            "3. low": "429.8300",
            "4. close": "441.1000",
            "5. volume": "1597019"
        },
        "2025-10-06 07:00:00": {
            "1. open": "440.0300",
            "2. high": "440.3000",
            "3. low": "437.4000",
            "4. close": "439.2400",
            "5. volume": "474308"
        },
        "2025-10-06 06:00:00": {
            "1. open": "439.4200",
            "2. high": "440.6700",
            "3. low": "439.3000",
            "4. close": "440.0300",
            "5. volume": "425430"
        },
        "2025-10-06 05:00:00": {
            "1. open": "438.1000",
            "2. high": "439.4500",
            "3. low": "437.4500",
            "4. close": "439.3900",
            "5. volume": "288660"
        },
        "2025-10-06 04:00:00": {
            "1. open": "436.3800",
            "2. high": "438.8400",
            "3. low": "433.1600",
            "4. close": "438.0700",
            "5. volume": "486340"
        },
        "2025-10-03 19:00:00": {
            "1. open": "430.4000",
            "2. high": "430.8000",
            "3. low": "428.6700",
            "4. close": "429.9600",
            "5. volume": "285449"
        },
        "2025-10-03 18:00:00": {
            "1. open": "430.7500",
            "2. high": "431.0000",
            "3. low": "430.0200",
            "4. close": "430.4000",
            "5. volume": "173518"
        },
        "2025-10-03 17:00:00": {
            "1. open": "429.8987",
            "2. high": "457.4448",
            "3. low": "400.4836",
            "4. close": "430.7600",
            "5. volume": "302853"
        },
        "2025-10-03 16:00:00": {
            "1. open": "429.8300",
            "2. high": "430.1500",
            "3. low": "428.2400",
            "4. close": "429.9000",
            "5. volume": "8170464"
        },
        "2025-10-03 15:00:00": {
            "1. open": "423.1800",
            "2. high": "430.2274",
            "3. low": "422.9108",
            "4. close": "429.8400",
            "5. volume": "18724109"
        },
        "2025-10-03 14:00:00": {
            "1. open": "419.5400",
            "2. high": "446.0000",
            "3. low": "417.6400",
            "4. close": "423.2100",
            "5. volume": "13693828"
        },
        "2025-10-03 13:00:00": {
            "1. open": "424.1200",
            "2. high": "424.1300",
            "3. low": "416.5750",
            "4. close": "419.5300",
            "5. volume": "19234482"
        },
        "2025-10-03 12:00:00": {
            "1. open": "430.2509",
            "2. high": "430.3800",
            "3. low": "423.9000",
            "4. close": "424.1731",
            "5. volume": "11726222"
        },
        "2025-10-03 11:00:00": {
            "1. open": "427.4500",
            "2. high": "431.8500",
            "3. low": "426.0700",
            "4. close": "430.2551",
            "5. volume": "15673502"
        },
        "2025-10-03 10:00:00": {
            "1. open": "438.2300",
            "2. high": "443.9700",
            "3. low": "424.7200",
            "4. close": "427.3936",
            "5. volume": "29286779"
        },
        "2025-10-03 09:00:00": {
            "1. open": "441.3865",
            "2. high": "446.7700",
            "3. low": "436.2800",
            "4. close": "438.1650",
            "5. volume": "16030107"
        },
        "2025-10-03 08:00:00": {
            "1. open": "444.6100",
            "2. high": "444.9700",
            "3. low": "436.0000",
            "4. close": "441.3900",
            "5. volume": "1844459"
        },
        "2025-10-03 07:00:00": {
            "1. open": "440.8400",
            "2. high": "442.9600",
            "3. low": "440.6600",
            "4. close": "442.3200",
            "5. volume": "332211"
        },
        "2025-10-03 06:00:00": {
            "1. open": "442.8800",
            "2. high": "443.2700",
            "3. low": "440.1800",
            "4. close": "440.9300",
            "5. volume": "240823"
        },
        "2025-10-03 05:00:00": {
            "1. open": "443.8300",
            "2. high": "444.1500",
            "3. low": "442.4000",
            "4. close": "442.9100",
            "5. volume": "195627"
        },
        "2025-10-03 04:00:00": {
            "1. open": "442.4000",
            "2. high": "444.9900",
            "3. low": "440.8400",
            "4. close": "443.8000",
            "5. volume": "585732"
        },
        "2025-10-02 19:00:00": {
            "1. open": "438.7000",
            "2. high": "439.8800",
            "3. low": "438.3500",
            "4. close": "439.3500",
            "5. volume": "407735"
        },
        "2025-10-02 18:00:00": {
            "1. open": "437.8000",
            "2. high": "439.4000",
            "3. low": "437.6500",
            "4. close": "438.6500",
            "5. volume": "514402"
        },
        "2025-10-02 17:00:00": {
            "1. open": "437.6700",
            "2. high": "662.7795",
            "3. low": "252.8013",
            "4. close": "437.8000",
            "5. volume": "455973"
        },
        "2025-10-02 16:00:00": {
            "1. open": "435.9800",
            "2. high": "437.9900",
            "3. low": "368.8100",
            "4. close": "437.7300",
            "5. volume": "8441436"
        },
        "2025-10-02 15:00:00": {
            "1. open": "441.0200",
            "2. high": "444.2000",
            "3. low": "435.5700",
            "4. close": "435.9700",
            "5. volume": "18417665"
        },
        "2025-10-02 14:00:00": {
            "1. open": "441.0150",
            "2. high": "443.3000",
            "3. low": "438.4400",
            "4. close": "441.0400",
            "5. volume": "11697532"
        },
        "2025-10-02 13:00:00": {
            "1. open": "444.0200",
            "2. high": "446.7800",
            "3. low": "439.6000",
            "4. close": "441.0300",
            "5. volume": "13928189"
        },
        "2025-10-02 12:00:00": {
            "1. open": "447.5300",
            "2. high": "449.0160",
            "3. low": "441.4500",
            "4. close": "444.0600",
            "5. volume": "12728497"
        },
        "2025-10-02 11:00:00": {
            "1. open": "452.7905",
            "2. high": "454.3600",
            "3. low": "444.7200",
            "4. close": "447.5900",
            "5. volume": "20428260"
        },
        "2025-10-02 10:00:00": {
            "1. open": "456.7300",
            "2. high": "459.5499",
            "3. low": "451.7000",
            "4. close": "452.8000",
            "5. volume": "18967141"
        },
        "2025-10-02 09:00:00": {
            "1. open": "467.9900",
            "2. high": "479.4400",
            "3. low": "437.6500",
            "4. close": "456.6513",
            "5. volume": "30390619"
        },
        "2025-10-02 08:00:00": {
            "1. open": "468.2400",
            "2. high": "468.9800",
            "3. low": "383.4649",
            "4. close": "467.9001",
            "5. volume": "2522078"
        },
        "2025-10-02 07:00:00": {
            "1. open": "466.4400",
            "2. high": "468.3000",
            "3. low": "466.1500",
            "4. close": "468.2400",
            "5. volume": "547708"
        },
        "2025-10-02 06:00:00": {
            "1. open": "466.0400",
            "2. high": "466.8600",
            "3. low": "465.8500",
            "4. close": "466.4500",
            "5. volume": "211691"
        },
        "2025-10-02 05:00:00": {
            "1. open": "466.4000",
            "2. high": "466.5000",
            "3. low": "465.3000",
            "4. close": "466.0000",
            "5. volume": "215874"
        },
        "2025-10-02 04:00:00": {
            "1. open": "463.2900",
            "2. high": "466.8300",
            "3. low": "460.2300",
            "4. close": "466.4100",
            "5. volume": "573806"
        },
        "2025-10-01 19:00:00": {
            "1. open": "460.7600",
            "2. high": "461.6500",
            "3. low": "460.6000",
            "4. close": "461.3800",
            "5. volume": "264418"
        },
        "2025-10-01 18:00:00": {
            "1. open": "459.0800",
            "2. high": "461.3900",
            "3. low": "348.3099",
            "4. close": "460.6800",
            "5. volume": "291346"
        },
        "2025-10-01 17:00:00": {
            "1. open": "303.0470",
            "2. high": "592.6153",
            "3. low": "221.9292",
            "4. close": "459.0600",
            "5. volume": "152466"
        },
        "2025-10-01 16:00:00": {
            "1. open": "459.4100",
            "2. high": "592.6153",
            "3. low": "221.9292",
            "4. close": "319.0725",
            "5. volume": "9159600"
        },
        "2025-10-01 15:00:00": {
            "1. open": "460.1300",
            "2. high": "462.2900",
            "3. low": "459.0100",
            "4. close": "459.4700",
            "5. volume": "13163759"
        },
        "2025-10-01 14:00:00": {
            "1. open": "458.3200",
            "2. high": "461.1866",
            "3. low": "458.0024",
            "4. close": "460.1050",
            "5. volume": "8989355"
        },
        "2025-10-01 13:00:00": {
            "1. open": "456.9600",
            "2. high": "460.2900",
            "3. low": "456.8700",
            "4. close": "458.3200",
            "5. volume": "11629434"
        },
        "2025-10-01 12:00:00": {
            "1. open": "455.4700",
            "2. high": "458.5100",
            "3. low": "454.1800",
            "4. close": "456.9376",
            "5. volume": "8629724"
        },
        "2025-10-01 11:00:00": {
            "1. open": "458.6659",
            "2. high": "458.8800",
            "3. low": "451.0000",
            "4. close": "455.4518",
            "5. volume": "11295884"
        },
        "2025-10-01 10:00:00": {
            "1. open": "445.7200",
            "2. high": "458.7799",
            "3. low": "445.1500",
            "4. close": "458.6800",
            "5. volume": "22907555"
        },
        "2025-10-01 09:00:00": {
            "1. open": "442.2800",
            "2. high": "449.5000",
            "3. low": "440.7500",
            "4. close": "445.7000",
            "5. volume": "13814195"
        },
        "2025-10-01 08:00:00": {
            "1. open": "439.5700",
            "2. high": "444.7200",
            "3. low": "437.6700",
            "4. close": "442.3000",
            "5. volume": "1015589"
        },
        "2025-10-01 07:00:00": {
            "1. open": "441.8600",
            "2. high": "444.0000",
            "3. low": "441.8000",
            "4. close": "443.6200",
            "5. volume": "204336"
        },
        "2025-10-01 06:00:00": {
            "1. open": "441.0800",
            "2. high": "442.3300",
            "3. low": "441.0700",
            "4. close": "441.8600",
            "5. volume": "123180"
        },
        "2025-10-01 05:00:00": {
            "1. open": "440.4200",
            "2. high": "441.7300",
            "3. low": "440.2000",
            "4. close": "441.1300",
            "5. volume": "104690"
        },
        "2025-10-01 04:00:00": {
            "1. open": "439.0000",
            "2. high": "441.1900",
            "3. low": "438.4300",
            "4. close": "440.4900",
            "5. volume": "215992"
        },
        "2025-09-30 19:00:00": {
            "1. open": "443.0900",
            "2. high": "443.5000",
            "3. low": "442.0000",
            "4. close": "442.1996",
            "5. volume": "213541"
        },
        "2025-09-30 18:00:00": {
            "1. open": "443.6700",
            "2. high": "444.0400",
            "3. low": "443.0000",
            "4. close": "443.0100",
            "5. volume": "145702"
        },
        "2025-09-30 17:00:00": {
            "1. open": "443.8600",
            "2. high": "459.4827",
            "3. low": "413.3675",
            "4. close": "443.6700",
            "5. volume": "209603"
        },
        "2025-09-30 16:00:00": {
            "1. open": "444.5300",
            "2. high": "453.5222",
            "3. low": "317.6600",
            "4. close": "443.8500",
            "5. volume": "6861313"
        },
        "2025-09-30 15:00:00": {
            "1. open": "442.0100",
            "2. high": "445.0000",
            "3. low": "441.2550",
            "4. close": "444.5400",
            "5. volume": "11365328"
        },
        "2025-09-30 14:00:00": {
            "1. open": "438.3000",
            "2. high": "444.4100",
            "3. low": "438.2401",
            "4. close": "441.9800",
            "5. volume": "10808834"
        },
        "2025-09-30 13:00:00": {
            "1. open": "436.8150",
            "2. high": "439.7800",
            "3. low": "436.1700",
            "4. close": "438.3350",
            "5. volume": "6634396"
        },
        "2025-09-30 12:00:00": {
            "1. open": "435.4900",
            "2. high": "437.1500",
            "3. low": "434.5100",
            "4. close": "436.8034",
            "5. volume": "6530973"
        },
        "2025-09-30 11:00:00": {
            "1. open": "439.9635",
            "2. high": "440.8000",
            "3. low": "433.1200",
            "4. close": "435.4650",
            "5. volume": "10611839"
        },
        "2025-09-30 10:00:00": {
            "1. open": "438.4300",
            "2. high": "440.2100",
            "3. low": "436.7800",
            "4. close": "439.9750",
            "5. volume": "10951557"
        },
        "2025-09-30 09:00:00": {
            "1. open": "441.2000",
            "2. high": "443.5799",
            "3. low": "436.7100",
            "4. close": "438.4000",
            "5. volume": "10961782"
        },
        "2025-09-30 08:00:00": {
            "1. open": "443.2100",
            "2. high": "443.2100",
            "3. low": "436.6162",
            "4. close": "441.1280",
            "5. volume": "798186"
        },
        "2025-09-30 07:00:00": {
            "1. open": "439.0000",
            "2. high": "441.5000",
            "3. low": "438.8800",
            "4. close": "440.8100",
            "5. volume": "303830"
        },
        "2025-09-30 06:00:00": {
            "1. open": "439.0300",
            "2. high": "440.2700",
            "3. low": "436.5000",
            "4. close": "438.9900",
            "5. volume": "272698"
        },
        "2025-09-30 05:00:00": {
            "1. open": "441.6300",
            "2. high": "441.6300",
            "3. low": "438.4000",
            "4. close": "439.0500",
            "5. volume": "194630"
        },
        "2025-09-30 04:00:00": {
            "1. open": "441.3300",
            "2. high": "443.3900",
            "3. low": "440.0000",
            "4. close": "441.4900",
            "5. volume": "161244"
        },
        "2025-09-29 19:00:00": {
            "1. open": "442.3500",
            "2. high": "442.4600",
            "3. low": "441.5300",
            "4. close": "441.8700",
            "5. volume": "126092"
        },
        "2025-09-29 18:00:00": {
            "1. open": "441.9100",
            "2. high": "442.6800",
            "3. low": "441.3800",
            "4. close": "442.3450",
            "5. volume": "116257"
        },
        "2025-09-29 17:00:00": {
            "1. open": "441.7000",
            "2. high": "450.0599",
            "3. low": "414.2383",
            "4. close": "441.9100",
            "5. volume": "408522"
        },
        "2025-09-29 16:00:00": {
            "1. open": "443.2100",
            "2. high": "443.6600",
            "3. low": "414.2383",
            "4. close": "441.7200",
            "5. volume": "6382597"
        },
        "2025-09-29 15:00:00": {
            "1. open": "442.3709",
            "2. high": "443.6400",
            "3. low": "440.3900",
            "4. close": "443.2200",
            "5. volume": "8491267"
        },
        "2025-09-29 14:00:00": {
            "1. open": "442.3800",
            "2. high": "443.8500",
            "3. low": "441.8000",
            "4. close": "442.3383",
            "5. volume": "6072026"
        },
        "2025-09-29 13:00:00": {
            "1. open": "441.6200",
            "2. high": "442.5800",
            "3. low": "439.6800",
            "4. close": "442.3700",
            "5. volume": "6458237"
        },
        "2025-09-29 12:00:00": {
            "1. open": "440.6612",
            "2. high": "442.7300",
            "3. low": "439.8500",
            "4. close": "441.5950",
            "5. volume": "7228593"
        },
        "2025-09-29 11:00:00": {
            "1. open": "442.7300",
            "2. high": "444.8900",
            "3. low": "439.5000",
            "4. close": "440.6660",
            "5. volume": "11121367"
        },
        "2025-09-29 10:00:00": {
            "1. open": "444.4100",
            "2. high": "446.4900",
            "3. low": "440.9400",
            "4. close": "442.7600",
            "5. volume": "14826409"
        },
        "2025-09-29 09:00:00": {
            "1. open": "446.8400",
            "2. high": "450.9800",
            "3. low": "440.4000",
            "4. close": "444.4100",
            "5. volume": "18630274"
        },
        "2025-09-29 08:00:00": {
            "1. open": "444.0000",
            "2. high": "447.2428",
            "3. low": "440.4000",
            "4. close": "446.7800",
            "5. volume": "1647936"
        },
        "2025-09-29 07:00:00": {
            "1. open": "442.7700",
            "2. high": "443.6600",
            "3. low": "442.6500",
            "4. close": "443.3800",
            "5. volume": "231619"
        },
        "2025-09-29 06:00:00": {
            "1. open": "442.9400",
            "2. high": "443.8800",
            "3. low": "442.5000",
            "4. close": "442.7700",
            "5. volume": "133830"
        },
        "2025-09-29 05:00:00": {
            "1. open": "443.8000",
            "2. high": "444.2700",
            "3. low": "442.5800",
            "4. close": "442.8100",
            "5. volume": "143384"
        },
        "2025-09-29 04:00:00": {
            "1. open": "443.6000",
            "2. high": "444.4000",
            "3. low": "442.2500",
            "4. close": "443.8000",
            "5. volume": "354865"
        }
    }
}